gitfleet-0.2.8.dist-info/METADATA
gitfleet-0.2.8.dist-info/WHEEL
gitfleet-0.2.8.dist-info/license_files/LICENSE
GitFleet/__init__.pyi
GitFleet/providers/base.pyi
GitFleet/providers/__init__.pyi
GitFleet/providers/token_manager.py
GitFleet/providers/token_manager.pyi
GitFleet/providers/__init__.py
GitFleet/providers/github.py
GitFleet/providers/base.py
GitFleet/providers/github.pyi
GitFleet/__init__.py
GitFleet/utils/auth.py
GitFleet/utils/rate_limit.pyi
GitFleet/utils/__init__.pyi
GitFleet/utils/__init__.py
GitFleet/utils/auth.pyi
GitFleet/utils/rate_limit.py
GitFleet/utils/converters.py
GitFleet/utils/converters.pyi
GitFleet/models/__init__.pyi
GitFleet/models/__init__.py
GitFleet/models/repo.pyi
GitFleet/models/common.pyi
GitFleet/models/common.py
GitFleet/models/repo.py
GitFleet/docs/index.md
GitFleet/testing/__init__.py
GitFleet/testing/fixtures.py
GitFleet/testing/mocks.py
GitFleet/py.typed
GitFleet/GitFleet.cpython-313-darwin.so
gitfleet-0.2.8.dist-info/RECORD
