Metadata-Version: 2.1
Name: gitfleet
Version: 0.2.8
Classifier: Programming Language :: Python :: 3
Classifier: Programming Language :: Python :: 3.10
Classifier: Programming Language :: Python :: 3.11
Classifier: Programming Language :: Python :: 3.12
Classifier: Programming Language :: Rust
Classifier: License :: OSI Approved :: MIT License
Classifier: Development Status :: 4 - Beta
Classifier: Intended Audience :: Developers
Classifier: Topic :: Software Development :: Version Control :: Git
Requires-Dist: httpx >=0.24.0
Requires-Dist: pytest-asyncio >=0.26.0
Requires-Dist: cryptography >=44.0.2 ; extra == 'crypto'
Requires-Dist: pandas >=2.0.0 ; extra == 'pandas'
Requires-Dist: pydantic >=2.0.0 ; extra == 'pydantic'
Requires-Dist: black >=22.1.0 ; extra == 'dev'
Requires-Dist: isort >=5.10.1 ; extra == 'dev'
Requires-Dist: pytest >=6.0.0 ; extra == 'dev'
Requires-Dist: maturin >=1.8.3 ; extra == 'dev'
Requires-Dist: pandas >=2.0.0 ; extra == 'examples'
Requires-Dist: cryptography >=44.0.2 ; extra == 'examples'
Requires-Dist: cryptography >=44.0.2 ; extra == 'all'
Requires-Dist: pandas >=2.0.0 ; extra == 'all'
Requires-Dist: pydantic >=2.0.0 ; extra == 'all'
Provides-Extra: crypto
Provides-Extra: pandas
Provides-Extra: pydantic
Provides-Extra: dev
Provides-Extra: examples
Provides-Extra: all
License-File: LICENSE
Summary: GitFleet is a high-performance Python library (powered by Rust) for managing and analyzing Git repositories in bulk. It supports asynchronous cloning, parallel git blame and commit analysis using Rayon, and integrates with GitHub, GitLab, and BitBucket APIs. Designed for large-scale repository analysis, GitFleet handles API token rotation, monitors rate limits, and provides detailed progress tracking across operations.
Author: Ben Meddeb <bmeddeb@asu.edu>
Author-email: Ben <bmeddeb@asu.edu>
License: MIT OR Apache-2.0
Requires-Python: >=3.10
Project-URL: Homepage, https://github.com/bmeddeb/GitFleet
Project-URL: Bug Tracker, https://github.com/bmeddeb/GitFleet/issues
